{
  "swagger": "2.0",
  "info": {
    "title": "Auto-generated OAS of RealWorld using OOPS",
    "version": "1.0.0"
  },
  "paths": {
    "/api/articles": {
      "post": {
        "operationId": "apiArticlesPost",
        "parameters": [
          {
            "name": "Authorization",
            "in": "header",
            "description": "JWT token",
            "required": true,
            "type": "string"
          },
          {
            "name": "body",
            "in": "body",
            "description": "Article to create",
            "required": true,
            "schema": {
              "type": "object",
              "properties": {
                "article": {
                  "type": "object",
                  "properties": {
                    "title": {
                      "type": "string"
                    },
                    "description": {
                      "type": "string"
                    },
                    "body": {
                      "type": "string"
                    },
                    "tagList": {
                      "type": "array",
                      "items": {
                        "type": "string"
                      }
                    }
                  }
                }
              }
            }
          }
        ],
        "responses": {
          "201": {
            "description": "Created",
            "schema": {
              "type": "object",
              "properties": {
                "article": {
                  "type": "object",
                  "properties": {
                    "title": {
                      "type": "string"
                    },
                    "slug": {
                      "type": "string"
                    },
                    "description": {
                      "type": "string"
                    },
                    "body": {
                      "type": "string"
                    },
                    "createdAt": {
                      "type": "string"
                    },
                    "updatedAt": {
                      "type": "string"
                    },
                    "author": {
                      "type": "object",
                      "properties": {
                        "username": {
                          "type": "string"
                        },
                        "bio": {
                          "type": "string"
                        },
                        "image": {
                          "type": "string"
                        },
                        "following": {
                          "type": "boolean"
                        }
                      }
                    },
                    "tagList": {
                      "type": "array",
                      "items": {
                        "type": "string"
                      }
                    },
                    "favorited": {
                      "type": "boolean"
                    },
                    "favoritesCount": {
                      "type": "integer",
                      "format": "int64"
                    }
                  }
                }
              }
            }
          },
          "422": {
            "description": "Validation or database error",
            "schema": {
              "type": "object",
              "properties": {
                "errors": {
                  "type": "object",
                  "additionalProperties": {
                    "type": "string"
                  }
                }
              }
            }
          }
        }
      },
      "get": {
        "operationId": "apiArticlesGet",
        "parameters": [
          {
            "name": "tag",
            "in": "query",
            "required": false,
            "type": "string"
          },
          {
            "name": "author",
            "in": "query",
            "required": false,
            "type": "string"
          },
          {
            "name": "favorited",
            "in": "query",
            "required": false,
            "type": "string"
          },
          {
            "name": "limit",
            "in": "query",
            "required": false,
            "type": "string"
          },
          {
            "name": "offset",
            "in": "query",
            "required": false,
            "type": "string"
          }
        ],
        "responses": {
          "200": {
            "description": "OK",
            "schema": {
              "type": "object",
              "properties": {
                "articles": {
                  "type": "array",
                  "items": {
                    "type": "object"
                  }
                },
                "articlesCount": {
                  "type": "integer",
                  "format": "int32"
                }
              }
            }
          },
          "404": {
            "description": "Invalid param"
          }
        }
      }
    },
    "/articles/{slug}": {
      "put": {
        "operationId": "articlesSlugPut",
        "parameters": [
          {
            "name": "slug",
            "in": "path",
            "required": true,
            "type": "string"
          },
          {
            "name": "body",
            "in": "body",
            "description": "",
            "required": true,
            "schema": {
              "type": "object",
              "properties": {
                "article": {
                  "type": "object",
                  "properties": {
                    "title": {
                      "type": "string"
                    },
                    "description": {
                      "type": "string"
                    },
                    "body": {
                      "type": "string"
                    },
                    "tagList": {
                      "type": "array",
                      "items": {
                        "type": "string"
                      }
                    }
                  },
                  "required": [
                    "title"
                  ]
                }
              }
            }
          }
        ],
        "responses": {
          "200": {
            "description": "OK",
            "schema": {
              "type": "object",
              "properties": {
                "article": {
                  "type": "object",
                  "properties": {
                    "title": {
                      "type": "string"
                    },
                    "slug": {
                      "type": "string"
                    },
                    "description": {
                      "type": "string"
                    },
                    "body": {
                      "type": "string"
                    },
                    "createdAt": {
                      "type": "string"
                    },
                    "updatedAt": {
                      "type": "string"
                    },
                    "author": {
                      "type": "object",
                      "properties": {
                        "username": {
                          "type": "string"
                        },
                        "bio": {
                          "type": "string"
                        },
                        "image": {
                          "type": "string",
                          "x-nullable": true
                        },
                        "following": {
                          "type": "boolean"
                        }
                      }
                    },
                    "tagList": {
                      "type": "array",
                      "items": {
                        "type": "string"
                      }
                    },
                    "favorited": {
                      "type": "boolean"
                    },
                    "favoritesCount": {
                      "type": "integer",
                      "format": "int64"
                    }
                  }
                }
              }
            }
          },
          "404": {
            "description": "Not Found",
            "schema": {
              "type": "object",
              "properties": {
                "errors": {
                  "type": "object",
                  "additionalProperties": {
                    "type": "string"
                  }
                }
              }
            }
          },
          "422": {
            "description": "Validation error",
            "schema": {
              "type": "object",
              "properties": {
                "errors": {
                  "type": "object",
                  "additionalProperties": {
                    "type": "string"
                  }
                }
              }
            }
          }
        }
      },
      "delete": {
        "operationId": "articlesSlugDelete",
        "parameters": [
          {
            "name": "slug",
            "in": "path",
            "required": true,
            "type": "string"
          }
        ],
        "responses": {
          "200": {
            "description": "OK",
            "schema": {
              "type": "object",
              "properties": {
                "article": {
                  "type": "string"
                }
              }
            }
          },
          "404": {
            "description": "Not Found",
            "schema": {
              "type": "object",
              "properties": {
                "errors": {
                  "type": "object",
                  "additionalProperties": {
                    "type": "string"
                  }
                }
              }
            }
          }
        }
      }
    },
    "/api/articles/{slug}/favorite": {
      "post": {
        "operationId": "apiArticlesSlugFavoritePost",
        "parameters": [
          {
            "name": "slug",
            "in": "path",
            "required": true,
            "type": "string"
          }
        ],
        "responses": {
          "200": {
            "description": "OK",
            "schema": {
              "type": "object",
              "properties": {
                "article": {
                  "type": "object",
                  "properties": {
                    "slug": {
                      "type": "string"
                    },
                    "title": {
                      "type": "string"
                    },
                    "description": {
                      "type": "string"
                    },
                    "body": {
                      "type": "string"
                    },
                    "tagList": {
                      "type": "array",
                      "items": {
                        "type": "string"
                      }
                    },
                    "createdAt": {
                      "type": "string",
                      "format": "date-time"
                    },
                    "updatedAt": {
                      "type": "string",
                      "format": "date-time"
                    },
                    "favorited": {
                      "type": "boolean"
                    },
                    "favoritesCount": {
                      "type": "integer"
                    },
                    "author": {
                      "type": "object",
                      "properties": {
                        "username": {
                          "type": "string"
                        },
                        "bio": {
                          "type": "string"
                        },
                        "image": {
                          "type": "string"
                        },
                        "following": {
                          "type": "boolean"
                        }
                      }
                    }
                  }
                }
              }
            }
          },
          "404": {
            "description": "Invalid slug",
            "schema": {
              "type": "object",
              "properties": {
                "errors": {
                  "type": "object",
                  "properties": {
                    "articles": {
                      "type": "array",
                      "items": {
                        "type": "string"
                      }
                    }
                  }
                }
              }
            }
          }
        }
      },
      "delete": {
        "operationId": "apiArticlesSlugFavoriteDelete",
        "parameters": [
          {
            "name": "slug",
            "in": "path",
            "description": "Slug of the article",
            "required": true,
            "type": "string"
          }
        ],
        "responses": {
          "200": {
            "description": "OK",
            "schema": {
              "type": "object",
              "properties": {
                "article": {
                  "type": "object",
                  "properties": {
                    "title": {
                      "type": "string"
                    },
                    "slug": {
                      "type": "string"
                    },
                    "description": {
                      "type": "string"
                    },
                    "body": {
                      "type": "string"
                    },
                    "createdAt": {
                      "type": "string",
                      "format": "date-time"
                    },
                    "updatedAt": {
                      "type": "string",
                      "format": "date-time"
                    },
                    "author": {
                      "type": "object",
                      "properties": {
                        "username": {
                          "type": "string"
                        },
                        "bio": {
                          "type": "string"
                        },
                        "image": {
                          "type": [
                            "string",
                            "null"
                          ]
                        },
                        "following": {
                          "type": "boolean"
                        }
                      }
                    },
                    "tagList": {
                      "type": "array",
                      "items": {
                        "type": "string"
                      }
                    },
                    "favorited": {
                      "type": "boolean"
                    },
                    "favoritesCount": {
                      "type": "integer"
                    }
                  }
                }
              }
            }
          },
          "404": {
            "description": "Not Found",
            "schema": {
              "type": "object",
              "properties": {
                "errors": {
                  "type": "object",
                  "additionalProperties": {
                    "type": "string"
                  }
                }
              }
            }
          }
        }
      }
    },
    "/api/articles/{slug}/comments": {
      "post": {
        "operationId": "apiArticlesSlugCommentsPost",
        "parameters": [
          {
            "name": "slug",
            "in": "path",
            "required": true,
            "type": "string"
          },
          {
            "name": "body",
            "in": "body",
            "description": "",
            "required": true,
            "schema": {
              "type": "object",
              "required": [
                "comment"
              ],
              "properties": {
                "comment": {
                  "type": "object",
                  "required": [
                    "body"
                  ],
                  "properties": {
                    "body": {
                      "type": "string"
                    }
                  }
                }
              }
            }
          }
        ],
        "responses": {
          "201": {
            "description": "Comment created",
            "schema": {
              "type": "object",
              "properties": {
                "comment": {
                  "type": "object",
                  "properties": {
                    "id": {
                      "type": "integer",
                      "format": "int64"
                    },
                    "body": {
                      "type": "string"
                    },
                    "createdAt": {
                      "type": "string"
                    },
                    "updatedAt": {
                      "type": "string"
                    },
                    "author": {
                      "type": "object",
                      "properties": {
                        "username": {
                          "type": "string"
                        },
                        "bio": {
                          "type": "string"
                        },
                        "image": {
                          "type": "string"
                        },
                        "following": {
                          "type": "boolean"
                        }
                      }
                    }
                  }
                }
              }
            }
          },
          "404": {
            "description": "Not Found",
            "schema": {
              "type": "object",
              "properties": {
                "errors": {
                  "type": "object",
                  "additionalProperties": {
                    "type": "string"
                  }
                }
              }
            }
          },
          "422": {
            "description": "Unprocessable Entity",
            "schema": {
              "type": "object",
              "properties": {
                "errors": {
                  "type": "object",
                  "additionalProperties": {
                    "type": "string"
                  }
                }
              }
            }
          }
        }
      },
      "get": {
        "operationId": "apiArticlesSlugCommentsGet",
        "parameters": [
          {
            "name": "slug",
            "in": "path",
            "required": true,
            "type": "string"
          }
        ],
        "responses": {
          "200": {
            "description": "OK",
            "schema": {
              "type": "object",
              "properties": {
                "comments": {
                  "type": "array",
                  "items": {
                    "type": "object",
                    "properties": {
                      "id": {
                        "type": "integer",
                        "format": "int64"
                      },
                      "body": {
                        "type": "string"
                      },
                      "createdAt": {
                        "type": "string",
                        "format": "date-time"
                      },
                      "updatedAt": {
                        "type": "string",
                        "format": "date-time"
                      },
                      "author": {
                        "type": "object",
                        "properties": {
                          "username": {
                            "type": "string"
                          },
                          "bio": {
                            "type": "string"
                          },
                          "image": {
                            "type": "string"
                          },
                          "following": {
                            "type": "boolean"
                          }
                        }
                      }
                    }
                  }
                }
              }
            }
          },
          "404": {
            "description": "Not Found",
            "schema": {
              "type": "object",
              "properties": {
                "errors": {
                  "type": "object",
                  "additionalProperties": {
                    "type": "array",
                    "items": {
                      "type": "string"
                    }
                  }
                }
              }
            }
          }
        }
      }
    },
    "/api/articles/{slug}/comments/{id}": {
      "delete": {
        "operationId": "apiArticlesSlugCommentsIdDelete",
        "parameters": [
          {
            "name": "slug",
            "in": "path",
            "required": true,
            "type": "string"
          },
          {
            "name": "id",
            "in": "path",
            "required": true,
            "type": "integer",
            "format": "int64"
          }
        ],
        "responses": {
          "200": {
            "description": "OK",
            "schema": {
              "type": "object",
              "properties": {
                "comment": {
                  "type": "string"
                }
              }
            }
          },
          "404": {
            "description": "Not Found",
            "schema": {
              "type": "object",
              "properties": {
                "errors": {
                  "type": "object",
                  "additionalProperties": {
                    "type": "array",
                    "items": {
                      "type": "string"
                    }
                  }
                }
              }
            }
          }
        }
      }
    },
    "/api/articles/{slug}": {
      "get": {
        "operationId": "apiArticlesSlugGet",
        "parameters": [
          {
            "name": "slug",
            "in": "path",
            "required": true,
            "type": "string",
            "description": "Slug of the article to retrieve"
          }
        ],
        "responses": {
          "200": {
            "description": "OK",
            "schema": {
              "type": "object",
              "properties": {
                "article": {
                  "type": "object",
                  "properties": {
                    "slug": {
                      "type": "string"
                    },
                    "title": {
                      "type": "string"
                    },
                    "description": {
                      "type": "string"
                    },
                    "body": {
                      "type": "string"
                    },
                    "createdAt": {
                      "type": "string",
                      "format": "date-time"
                    },
                    "updatedAt": {
                      "type": "string",
                      "format": "date-time"
                    },
                    "author": {
                      "type": "object",
                      "properties": {
                        "username": {
                          "type": "string"
                        },
                        "bio": {
                          "type": "string"
                        },
                        "image": {
                          "type": "string"
                        },
                        "following": {
                          "type": "boolean"
                        }
                      }
                    },
                    "tagList": {
                      "type": "array",
                      "items": {
                        "type": "string"
                      }
                    },
                    "favorited": {
                      "type": "boolean"
                    },
                    "favoritesCount": {
                      "type": "integer",
                      "format": "int32"
                    }
                  }
                }
              }
            }
          },
          "404": {
            "description": "Invalid slug",
            "schema": {
              "type": "object",
              "properties": {
                "errors": {
                  "type": "object",
                  "additionalProperties": {
                    "type": "string"
                  }
                }
              }
            }
          }
        }
      }
    },
    "/api/tags": {
      "get": {
        "operationId": "apiTagsGet",
        "parameters": [],
        "responses": {
          "200": {
            "description": "successful operation",
            "schema": {
              "type": "object",
              "properties": {
                "tags": {
                  "type": "array",
                  "items": {
                    "type": "string"
                  }
                }
              }
            }
          },
          "404": {
            "description": "not found",
            "schema": {
              "type": "object",
              "properties": {
                "errors": {
                  "type": "object",
                  "additionalProperties": {
                    "type": "string"
                  }
                }
              }
            }
          }
        }
      }
    },
    "/api/profiles/{username}": {
      "get": {
        "operationId": "apiProfilesUsernameGet",
        "parameters": [
          {
            "name": "username",
            "in": "path",
            "required": true,
            "type": "string"
          }
        ],
        "responses": {
          "200": {
            "description": "OK",
            "schema": {
              "type": "object",
              "properties": {
                "profile": {
                  "type": "object",
                  "properties": {
                    "username": {
                      "type": "string"
                    },
                    "bio": {
                      "type": "string"
                    },
                    "image": {
                      "type": "string"
                    },
                    "following": {
                      "type": "boolean"
                    }
                  },
                  "required": [
                    "username",
                    "bio",
                    "image",
                    "following"
                  ]
                }
              },
              "required": [
                "profile"
              ]
            }
          },
          "404": {
            "description": "Not Found",
            "schema": {
              "type": "object",
              "properties": {
                "errors": {
                  "type": "object",
                  "additionalProperties": {
                    "type": "array",
                    "items": {
                      "type": "string"
                    }
                  }
                }
              },
              "required": [
                "errors"
              ]
            }
          }
        }
      }
    },
    "/api/profiles/{username}/follow": {
      "post": {
        "operationId": "apiProfilesUsernameFollowPost",
        "parameters": [
          {
            "name": "username",
            "in": "path",
            "required": true,
            "type": "string",
            "description": "Username of the profile to follow"
          }
        ],
        "responses": {
          "200": {
            "description": "OK",
            "schema": {
              "type": "object",
              "properties": {
                "profile": {
                  "type": "object",
                  "properties": {
                    "username": {
                      "type": "string"
                    },
                    "bio": {
                      "type": "string"
                    },
                    "image": {
                      "type": "string"
                    },
                    "following": {
                      "type": "boolean"
                    }
                  }
                }
              }
            }
          },
          "404": {
            "description": "Invalid username",
            "schema": {
              "type": "object",
              "properties": {
                "errors": {
                  "type": "object",
                  "properties": {
                    "profile": {
                      "type": "array",
                      "items": {
                        "type": "string"
                      }
                    }
                  }
                }
              }
            }
          },
          "422": {
            "description": "Unprocessable Entity",
            "schema": {
              "type": "object",
              "properties": {
                "errors": {
                  "type": "object",
                  "properties": {
                    "database": {
                      "type": "array",
                      "items": {
                        "type": "string"
                      }
                    }
                  }
                }
              }
            }
          }
        }
      }
    },
    "/profiles/{username}/follow": {
      "post": {
        "operationId": "profilesUsernameFollowPost",
        "parameters": [
          {
            "name": "username",
            "in": "path",
            "required": true,
            "type": "string"
          }
        ],
        "responses": {
          "200": {
            "description": "OK",
            "schema": {
              "type": "object",
              "properties": {
                "profile": {
                  "type": "object",
                  "properties": {
                    "username": {
                      "type": "string"
                    },
                    "bio": {
                      "type": "string"
                    },
                    "image": {
                      "type": "string",
                      "x-nullable": true
                    },
                    "following": {
                      "type": "boolean"
                    }
                  }
                }
              }
            }
          },
          "404": {
            "description": "Not Found",
            "schema": {
              "type": "object",
              "properties": {
                "errors": {
                  "type": "object",
                  "properties": {
                    "profile": {
                      "type": "string"
                    }
                  }
                }
              }
            }
          },
          "422": {
            "description": "Unprocessable Entity",
            "schema": {
              "type": "object",
              "properties": {
                "errors": {
                  "type": "object",
                  "properties": {
                    "database": {
                      "type": "string"
                    }
                  }
                }
              }
            }
          }
        }
      },
      "delete": {
        "operationId": "profilesUsernameFollowDelete",
        "parameters": [
          {
            "name": "username",
            "in": "path",
            "required": true,
            "type": "string"
          }
        ],
        "responses": {
          "200": {
            "description": "Profile unfollowed",
            "schema": {
              "type": "object",
              "properties": {
                "profile": {
                  "type": "object",
                  "properties": {
                    "username": {
                      "type": "string"
                    },
                    "bio": {
                      "type": "string"
                    },
                    "image": {
                      "type": "string"
                    },
                    "following": {
                      "type": "boolean"
                    }
                  }
                }
              }
            }
          },
          "404": {
            "description": "Profile not found",
            "schema": {
              "type": "object",
              "properties": {
                "errors": {
                  "type": "object",
                  "additionalProperties": {
                    "type": "string"
                  }
                }
              }
            }
          },
          "422": {
            "description": "Unprocessable Entity",
            "schema": {
              "type": "object",
              "properties": {
                "errors": {
                  "type": "object",
                  "additionalProperties": {
                    "type": "string"
                  }
                }
              }
            }
          }
        }
      }
    },
    "/api/users": {
      "post": {
        "operationId": "apiUsersPost",
        "parameters": [
          {
            "name": "body",
            "in": "body",
            "description": "",
            "required": true,
            "schema": {
              "type": "object",
              "properties": {
                "username": {
                  "type": "string",
                  "minLength": 4,
                  "maxLength": 255,
                  "pattern": "^[A-Za-z0-9]+$"
                },
                "email": {
                  "type": "string",
                  "format": "email"
                },
                "password": {
                  "type": "string",
                  "minLength": 8,
                  "maxLength": 255
                },
                "bio": {
                  "type": "string",
                  "maxLength": 1024
                },
                "image": {
                  "type": "string",
                  "format": "url"
                }
              },
              "required": [
                "username",
                "email",
                "password"
              ]
            }
          }
        ],
        "responses": {
          "201": {
            "description": "User created",
            "schema": {
              "type": "object",
              "properties": {
                "user": {
                  "type": "object",
                  "properties": {
                    "username": {
                      "type": "string"
                    },
                    "email": {
                      "type": "string"
                    },
                    "bio": {
                      "type": "string"
                    },
                    "image": {
                      "type": "string"
                    },
                    "token": {
                      "type": "string"
                    }
                  }
                }
              }
            }
          },
          "422": {
            "description": "Validation or database error",
            "schema": {
              "type": "object",
              "properties": {
                "errors": {
                  "type": "object",
                  "additionalProperties": {
                    "type": "string"
                  }
                }
              }
            }
          }
        }
      }
    },
    "/api/users/login": {
      "post": {
        "operationId": "apiUsersLoginPost",
        "parameters": [
          {
            "name": "body",
            "in": "body",
            "description": "",
            "required": true,
            "schema": {
              "type": "object",
              "properties": {
                "user": {
                  "type": "object",
                  "properties": {
                    "email": {
                      "type": "string",
                      "format": "email"
                    },
                    "password": {
                      "type": "string",
                      "format": "password"
                    }
                  },
                  "required": [
                    "email",
                    "password"
                  ]
                }
              },
              "required": [
                "user"
              ]
            }
          }
        ],
        "responses": {
          "200": {
            "description": "OK",
            "schema": {
              "type": "object",
              "properties": {
                "user": {
                  "type": "object",
                  "properties": {
                    "username": {
                      "type": "string"
                    },
                    "email": {
                      "type": "string",
                      "format": "email"
                    },
                    "bio": {
                      "type": "string"
                    },
                    "image": {
                      "type": "string"
                    },
                    "token": {
                      "type": "string"
                    }
                  }
                }
              }
            }
          },
          "403": {
            "description": "Forbidden",
            "schema": {
              "type": "object",
              "properties": {
                "errors": {
                  "type": "object",
                  "additionalProperties": {
                    "type": "string"
                  }
                }
              }
            }
          },
          "422": {
            "description": "Unprocessable Entity",
            "schema": {
              "type": "object",
              "properties": {
                "errors": {
                  "type": "object",
                  "additionalProperties": {
                    "type": "string"
                  }
                }
              }
            }
          }
        }
      }
    },
    "/user": {
      "get": {
        "operationId": "userGet",
        "parameters": [
          {
            "name": "Authorization",
            "in": "header",
            "description": "Authentication token in the format 'Token <token>'",
            "required": true,
            "type": "string"
          }
        ],
        "responses": {
          "200": {
            "description": "OK",
            "schema": {
              "type": "object",
              "properties": {
                "user": {
                  "type": "object",
                  "properties": {
                    "username": {
                      "type": "string"
                    },
                    "email": {
                      "type": "string",
                      "format": "email"
                    },
                    "bio": {
                      "type": "string"
                    },
                    "image": {
                      "type": "string",
                      "x-nullable": true
                    },
                    "token": {
                      "type": "string"
                    }
                  },
                  "required": [
                    "username",
                    "email",
                    "bio",
                    "token"
                  ]
                }
              }
            }
          }
        }
      },
      "put": {
        "operationId": "userPut",
        "parameters": [
          {
            "name": "body",
            "in": "body",
            "description": "",
            "required": true,
            "schema": {
              "type": "object",
              "properties": {
                "user": {
                  "type": "object",
                  "required": [
                    "username",
                    "email",
                    "password"
                  ],
                  "properties": {
                    "username": {
                      "type": "string"
                    },
                    "email": {
                      "type": "string"
                    },
                    "password": {
                      "type": "string"
                    },
                    "bio": {
                      "type": "string"
                    },
                    "image": {
                      "type": "string"
                    }
                  }
                }
              }
            }
          }
        ],
        "responses": {
          "200": {
            "description": "OK",
            "schema": {
              "type": "object",
              "properties": {
                "user": {
                  "type": "object",
                  "properties": {
                    "username": {
                      "type": "string"
                    },
                    "email": {
                      "type": "string"
                    },
                    "bio": {
                      "type": "string"
                    },
                    "image": {
                      "type": "string"
                    },
                    "token": {
                      "type": "string"
                    }
                  }
                }
              }
            }
          },
          "422": {
            "description": "Unprocessable Entity",
            "schema": {
              "type": "object",
              "properties": {
                "errors": {
                  "type": "object"
                }
              }
            }
          }
        }
      }
    },
    "/api/user": {
      "get": {
        "operationId": "apiUserGet",
        "parameters": [],
        "responses": {
          "200": {
            "description": "OK",
            "schema": {
              "type": "object",
              "properties": {
                "user": {
                  "type": "object",
                  "properties": {
                    "username": {
                      "type": "string"
                    },
                    "email": {
                      "type": "string"
                    },
                    "bio": {
                      "type": "string"
                    },
                    "image": {
                      "type": "string"
                    },
                    "token": {
                      "type": "string"
                    }
                  }
                }
              }
            }
          }
        }
      },
      "put": {
        "operationId": "apiUserPut",
        "parameters": [
          {
            "name": "body",
            "in": "body",
            "description": "",
            "required": true,
            "schema": {
              "type": "object",
              "properties": {
                "user": {
                  "type": "object",
                  "properties": {
                    "username": {
                      "type": "string"
                    },
                    "email": {
                      "type": "string",
                      "format": "email"
                    },
                    "password": {
                      "type": "string"
                    },
                    "bio": {
                      "type": "string"
                    },
                    "image": {
                      "type": "string"
                    }
                  },
                  "required": [
                    "username",
                    "email",
                    "password"
                  ]
                }
              }
            }
          }
        ],
        "responses": {
          "200": {
            "description": "OK",
            "schema": {
              "type": "object",
              "properties": {
                "user": {
                  "type": "object"
                }
              }
            }
          },
          "422": {
            "description": "Unprocessable Entity",
            "schema": {
              "type": "object"
            }
          }
        }
      }
    }
  }
}